sbercloud/__init__.py
sbercloud/sbercloud.py
sbercloud/settings.py
sbercloud/sfs/__init__.py
sbercloud/sfs/exceptions.py
sbercloud/sfs/sfs.py
sbercloud-0.1.0.dist-info/LICENSE
sbercloud-0.1.0.dist-info/WHEEL
sbercloud-0.1.0.dist-info/METADATA
sbercloud-0.1.0.dist-info/RECORD
