Metadata-Version: 2.1
Name: sbercloud
Version: 0.1.0
Summary: 
Author: Nikolay Baryshnikov
Author-email: root@k0d.ru
Requires-Python: >=3.8,<4.0
Classifier: Programming Language :: Python :: 3
Classifier: Programming Language :: Python :: 3.8
Classifier: Programming Language :: Python :: 3.9
Requires-Dist: pydantic (>=1.8.1,<2.0.0)
Requires-Dist: requests (>=2.25.1,<3.0.0)
